templus/__init__.py
templus/client.py
templus/objects.py
templus-1.5.dist-info/LICENSE
templus-1.5.dist-info/METADATA
templus-1.5.dist-info/WHEEL
templus-1.5.dist-info/top_level.txt
templus-1.5.dist-info/RECORD
