Metadata-Version: 2.1
Name: templus
Version: 1.5
Summary: library for reading and receiving messages from https://tempmail.plus/ru/#!
Home-page: https://github.com/BitterTruth1/templus
Author-email: bonnita1900432@gmail.com
License: UNKNOWN
Download-URL: https://github.com/BitterTruth1/templus/archive/refs/heads/main.zip
Platform: UNKNOWN
License-File: LICENSE
